tinytoken/__init__.py
tinytoken/cache.py
tinytoken/cli.py
tinytoken/exceptions.py
tinytoken/jwt.py
tinytoken/oauth.py
tinytoken/output.py
tinytoken/profile.py
tinytoken/server.py
tinytoken/user_agent.py
tinytoken/utils.py
tinytoken-0.9.5.dist-info/LICENSE
tinytoken-0.9.5.dist-info/METADATA
tinytoken-0.9.5.dist-info/WHEEL
tinytoken-0.9.5.dist-info/entry_points.txt
tinytoken-0.9.5.dist-info/top_level.txt
tinytoken-0.9.5.dist-info/RECORD
